xone/__init__.py
xone/browser.py
xone/cache.py
xone/calendar.py
xone/chart.py
xone/files.py
xone/logs.py
xone/procs.py
xone/profile.py
xone/utils.py
xone/xql.py
xone/tests/__init__.py
xone/tests/conftest.py
xone-0.1.7.dist-info/LICENSE
xone-0.1.7.dist-info/METADATA
xone-0.1.7.dist-info/WHEEL
xone-0.1.7.dist-info/top_level.txt
xone-0.1.7.dist-info/RECORD
