Metadata-Version: 2.1
Name: xone
Version: 0.1.7
Summary: Frequently used functions for financial data analysis
Home-page: https://github.com/alpha-xone/xone
Author: Alpha x1
Author-email: alpha.xone@outlook.com
License: Apache
Platform: UNKNOWN
Classifier: License :: OSI Approved :: Apache Software License
Classifier: Programming Language :: Python :: 3.6
Classifier: Programming Language :: Python :: 3.7
Classifier: Programming Language :: Python :: 3.8
Requires-Dist: matplotlib (>=3.0.2)
Requires-Dist: numpy (>=1.15.0)
Requires-Dist: pandas (>=1.0.0)
Requires-Dist: pyarrow (>=1.0.1)
Requires-Dist: pytz (>=2020.4)
Requires-Dist: parse (>=1.18.0)
Requires-Dist: tqdm (>=4.51.0)
Requires-Dist: beautifulsoup4 (>=4.9.0)
Requires-Dist: selenium (>=3.141.0)
Requires-Dist: requests (>=2.25.0)
